witcher.py
witcher_interpreter.py
witcherscript-1.3.0.dist-info/licenses/LICENSE
witcherscript-1.3.0.dist-info/METADATA
witcherscript-1.3.0.dist-info/WHEEL
witcherscript-1.3.0.dist-info/entry_points.txt
witcherscript-1.3.0.dist-info/top_level.txt
witcherscript-1.3.0.dist-info/RECORD
