Metadata-Version: 2.4
Name: witcherscript
Version: 1.3.0
Summary: A programming language inspired by The Witcher 3: Wild Hunt
Home-page: https://github.com/rwnicholas/WitcherScript
Author: WitcherScript Contributors
Project-URL: Bug Tracker, https://github.com/rwnicholas/WitcherScript/issues
Project-URL: Documentation, https://github.com/rwnicholas/WitcherScript/blob/main/README.md
Project-URL: Source Code, https://github.com/rwnicholas/WitcherScript
Keywords: programming language witcher interpreter game inspired
Classifier: Development Status :: 4 - Beta
Classifier: Environment :: Console
Classifier: Intended Audience :: Developers
Classifier: Intended Audience :: Education
Classifier: License :: OSI Approved :: MIT License
Classifier: Natural Language :: English
Classifier: Operating System :: OS Independent
Classifier: Programming Language :: Python :: 3
Classifier: Programming Language :: Python :: 3.6
Classifier: Programming Language :: Python :: 3.7
Classifier: Programming Language :: Python :: 3.8
Classifier: Programming Language :: Python :: 3.9
Classifier: Programming Language :: Python :: 3.10
Classifier: Programming Language :: Python :: 3.11
Classifier: Topic :: Education
Classifier: Topic :: Software Development :: Interpreters
Classifier: Topic :: System :: Shells
Requires-Python: >=3.6
License-File: LICENSE
Dynamic: author
Dynamic: classifier
Dynamic: description
Dynamic: description-content-type
Dynamic: home-page
Dynamic: keywords
Dynamic: license-file
Dynamic: project-url
Dynamic: requires-python
Dynamic: summary
